alu.v
// alu.v
module alu (
    input [2:0] opcode,
    input [7:0] operandA,
    input [7:0] operandB,
    output reg [7:0] result
);

always @(*) begin
    case (opcode)
        3'b000: result = operandA + operandB;       // ADD
        3'b001: result = operandA - operandB;       // SUB
        3'b010: result = operandA & operandB;       // AND
        3'b011: result = operandA | operandB;       // OR
        3'b100: result = operandA ^ operandB;       // XOR
        3'b101: result = ~operandA;                 // NOT (operandA only)
        3'b110: result = operandA << 1;             // Shift Left
        3'b111: result = operandA >> 1;             // Shift Right
        default: result = 8'd0;
    endcase
end

endmodule

alu_tb.v
// alu_tb.v
`timescale 1ns/1ps

module alu_tb;

reg [2:0] opcode;
reg [7:0] operandA, operandB;
wire [7:0] result;

// Instantiate the ALU
alu uut (
    .opcode(opcode),
    .operandA(operandA),
    .operandB(operandB),
    .result(result)
);

initial begin
    $dumpfile("alu_wave.vcd");  
    $dumpvars(0, alu_tb);       

    $monitor("Time=%0t | opcode=%b | A=%d | B=%d | result=%d", $time, opcode, operandA, operandB, result);

    operandA = 8'd15;
    operandB = 8'd5;

    opcode = 3'b000; #10;  // ADD
    opcode = 3'b001; #10;  // SUB
    opcode = 3'b010; #10;  // AND
    opcode = 3'b011; #10;  // OR
    opcode = 3'b100; #10;  // XOR
    opcode = 3'b101; #10;  // NOT (A)
    opcode = 3'b110; #10;  // Shift Left
    opcode = 3'b111; #10;  // Shift Right

    $finish;
end

endmodule

alu_wave.vcd
$date
	Wed Jul 16 12:42:18 2025
$end
$version
	Icarus Verilog
$end
$timescale
	1ps
$end
$scope module alu_tb $end
$var wire 8 ! result [7:0] $end
$var reg 3 " opcode [2:0] $end
$var reg 8 # operandA [7:0] $end
$var reg 8 $ operandB [7:0] $end
$scope module uut $end
$var wire 3 % opcode [2:0] $end
$var wire 8 & operandA [7:0] $end
$var wire 8 ' operandB [7:0] $end
$var reg 8 ( result [7:0] $end
$upscope $end
$upscope $end
$enddefinitions $end
#0
$dumpvars
b10100 (
b101 '
b1111 &
b0 %
b101 $
b1111 #
b0 "
b10100 !
$end
#10000
b1010 (
b1010 !
b1 "
b1 %
#20000
b101 (
b101 !
b10 "
b10 %
#30000
b1111 (
b1111 !
b11 "
b11 %
#40000
b1010 (
b1010 !
b100 "
b100 %
#50000
b11110 (
b11110 !
b101 "
b101 %
#60000
b111 (
b111 !
b110 "
b110 %
#70000
b0 (
b0 !
b111 "
b111 %
