fir_filter.v
`timescale 1ns/1ps

module fir_filter #(parameter N = 4)(
    input clk,
    input reset,
    input signed [7:0] x_in,
    output reg signed [15:0] y_out
);
    reg signed [7:0] h [0:N-1];
    reg signed [7:0] x_reg [0:N-1];
    reg signed [15:0] acc;
    integer i;

    initial begin
        h[0] = 8'd1;
        h[1] = 8'd2;
        h[2] = 8'd3;
        h[3] = 8'd4;
    end

    always @(posedge clk or posedge reset) begin
        if (reset) begin
            y_out <= 0;
            for (i = 0; i < N; i = i + 1)
                x_reg[i] <= 0;
        end else begin
            for (i = N-1; i > 0; i = i - 1)
                x_reg[i] <= x_reg[i-1];
            x_reg[0] <= x_in;

            acc = 0;
            for (i = 0; i < N; i = i + 1)
                acc = acc + x_reg[i] * h[i];
            y_out <= acc;
        end
    end
endmodule

fir_filter_tb.v
`timescale 1ns/1ps

module fir_filter_tb;
    reg clk;
    reg reset;
    reg signed [7:0] x_in;
    wire signed [15:0] y_out;

    fir_filter uut (
        .clk(clk),
        .reset(reset),
        .x_in(x_in),
        .y_out(y_out)
    );

    initial begin
        $dumpfile("dump.vcd");
        $dumpvars(0, fir_filter_tb);

        clk = 0;
        reset = 1;
        x_in = 0;
        #10 reset = 0;

        // Apply input samples
        #10 x_in = 8'd5;
        #10 x_in = 8'd4;
        #10 x_in = 8'd3;
        #10 x_in = 8'd2;
        #10 x_in = 8'd1;
        #10 x_in = 8'd0;

        #50 $finish;
    end

    always #5 clk = ~clk; // Clock generator
endmodule

fir_filter.vcd
$date
	Thu Jul 17 13:08:11 2025
$end
$version
	Icarus Verilog
$end
$timescale
	1ps
$end
$scope module fir_filter_tb $end
$var wire 16 ! y_out [15:0] $end
$var reg 1 " clk $end
$var reg 1 # reset $end
$var reg 8 $ x_in [7:0] $end
$scope module uut $end
$var wire 1 % clk $end
$var wire 1 & reset $end
$var wire 8 ' x_in [7:0] $end
$var reg 16 ( acc [15:0] $end
$var integer 32 ) i [31:0] $end
$var reg 16 * y_out [15:0] $end
$upscope $end
$upscope $end
$enddefinitions $end
#0
$dumpvars
b0 *
b100 )
bx (
b0 '
1&
0%
b0 $
1#
0"
b0 !
$end
#5000
b100 )
1"
1%
#10000
0"
0%
0#
0&
#15000
b0 (
b100 )
1"
1%
#20000
0"
0%
b101 $
b101 '
#25000
b100 )
1"
1%
#30000
0"
0%
b100 $
b100 '
#35000
b101 *
b101 !
b101 (
b100 )
1"
1%
#40000
0"
0%
b11 $
b11 '
#45000
b1110 *
b1110 !
b1110 (
b100 )
1"
1%
#50000
0"
0%
b10 $
b10 '
#55000
b11010 *
b11010 !
b11010 (
b100 )
1"
1%
#60000
0"
0%
b1 $
b1 '
#65000
b101000 *
b101000 !
b101000 (
b100 )
1"
1%
#70000
0"
0%
b0 $
b0 '
#75000
b11110 *
b11110 !
b11110 (
b100 )
1"
1%
#80000
0"
0%
#85000
b10100 *
b10100 !
b10100 (
b100 )
1"
1%
#90000
0"
0%
#95000
b1011 *
b1011 !
b1011 (
b100 )
1"
1%
#100000
0"
0%
#105000
b100 *
b100 !
b100 (
b100 )
1"
1%
#110000
0"
0%
#115000
b0 *
b0 !
b0 (
b100 )
1"
1%
