ram.v
module ram #(parameter ADDR_WIDTH = 4, DATA_WIDTH = 8)(
    input clk,
    input we,                   // Write enable
    input [ADDR_WIDTH-1:0] addr,
    input [DATA_WIDTH-1:0] din, // Data input
    output reg [DATA_WIDTH-1:0] dout // Data output
);

    // RAM storage
    reg [DATA_WIDTH-1:0] mem [0:(1<<ADDR_WIDTH)-1];

    always @(posedge clk) begin
        if (we)
            mem[addr] <= din;     // Write
        else
            dout <= mem[addr];    // Read
    end

endmodule

ram_tb.v
`timescale 1ns / 1ps

module ram_tb;
    reg clk;
    reg we;
    reg [3:0] addr;
    reg [7:0] din;
    wire [7:0] dout;

    // Instantiate the RAM
    ram uut (
        .clk(clk),
        .we(we),
        .addr(addr),
        .din(din),
        .dout(dout)
    );

    // Clock generation
    always #5 clk = ~clk;

    initial begin
        $dumpfile("ram_wave.vcd");
        $dumpvars(0, ram_tb);

        clk = 0; we = 0; addr = 0; din = 0;

        // Write some data
        #10 we = 1; addr = 4'h1; din = 8'hA5;
        #10 addr = 4'h2; din = 8'h3C;
        #10 addr = 4'h3; din = 8'hFF;

        // Read back the data
        #10 we = 0; addr = 4'h1;
        #10 addr = 4'h2;
        #10 addr = 4'h3;

        #10 $finish;
    end
endmodule

ram_wave.vcd
$date
	Wed Jul 16 12:17:06 2025
$end
$version
	Icarus Verilog
$end
$timescale
	1ps
$end
$scope module ram_tb $end
$var wire 8 ! dout [7:0] $end
$var reg 4 " addr [3:0] $end
$var reg 1 # clk $end
$var reg 8 $ din [7:0] $end
$var reg 1 % we $end
$scope module uut $end
$var wire 4 & addr [3:0] $end
$var wire 1 ' clk $end
$var wire 8 ( din [7:0] $end
$var wire 1 ) we $end
$var reg 8 * dout [7:0] $end
$upscope $end
$upscope $end
$enddefinitions $end
#0
$dumpvars
bx *
0)
b0 (
0'
b0 &
0%
b0 $
0#
b0 "
bx !
$end
#5000
1#
1'
#10000
0#
0'
b10100101 $
b10100101 (
b1 "
b1 &
1%
1)
#15000
1#
1'
#20000
0#
0'
b111100 $
b111100 (
b10 "
b10 &
#25000
1#
1'
#30000
0#
0'
b11111111 $
b11111111 (
b11 "
b11 &
#35000
1#
1'
#40000
0#
0'
b1 "
b1 &
0%
0)
#45000
b10100101 *
b10100101 !
1#
1'
#50000
0#
0'
b10 "
b10 &
#55000
b111100 *
b111100 !
1#
1'
#60000
0#
0'
b11 "
b11 &
#65000
b11111111 *
b11111111 !
1#
1'
