pipeline.v
`timescale 1ns/1ps

module pipeline_processor(input clk, input reset);

    // Instruction format: [15:12] opcode, [11:8] rs, [7:4] rt, [3:0] rd
    reg [15:0] instruction_memory [0:255];
    reg [7:0] data_memory [0:255];
    reg [7:0] registers [0:15];

    reg [7:0] pc;

    // Pipeline registers
    reg [15:0] IF_ID_instr;
    reg [15:0] ID_EX_instr;
    reg [7:0]  ID_EX_rs_val, ID_EX_rt_val;
    reg [3:0]  ID_EX_rd;

    reg [15:0] EX_MEM_instr;
    reg [7:0]  EX_MEM_alu_out, EX_MEM_rt_val;
    reg [3:0]  EX_MEM_rd;

    reg [15:0] MEM_WB_instr;
    reg [7:0]  MEM_WB_result;
    reg [3:0]  MEM_WB_rd;

    // Instruction decode wires
    wire [3:0] opcode = IF_ID_instr[15:12];
    wire [3:0] rs     = IF_ID_instr[11:8];
    wire [3:0] rt     = IF_ID_instr[7:4];
    wire [3:0] rd     = IF_ID_instr[3:0];

    always @(posedge clk or posedge reset) begin
        if (reset) begin
            pc <= 0;
            IF_ID_instr <= 0;
            ID_EX_instr <= 0;
            EX_MEM_instr <= 0;
            MEM_WB_instr <= 0;
        end else begin
            // FETCH
            IF_ID_instr <= instruction_memory[pc];
            pc <= pc + 1;

            // DECODE
            ID_EX_instr <= IF_ID_instr;
            ID_EX_rs_val <= registers[rs];
            ID_EX_rt_val <= registers[rt];
            ID_EX_rd <= rd;

            // EXECUTE
            EX_MEM_instr <= ID_EX_instr;
            EX_MEM_rt_val <= ID_EX_rt_val;
            EX_MEM_rd <= ID_EX_rd;

            case (ID_EX_instr[15:12])
                4'b0001: EX_MEM_alu_out <= ID_EX_rs_val + ID_EX_rt_val; // ADD
                4'b0010: EX_MEM_alu_out <= ID_EX_rs_val - ID_EX_rt_val; // SUB
                4'b0011: EX_MEM_alu_out <= data_memory[ID_EX_rs_val];   // LOAD
                4'b0100: begin // STORE
                    data_memory[ID_EX_rt_val] <= ID_EX_rs_val;
                    EX_MEM_alu_out <= 0;
                end
                default: EX_MEM_alu_out <= 0;
            endcase

            // MEMORY (pass-through)
            MEM_WB_instr <= EX_MEM_instr;
            MEM_WB_rd <= EX_MEM_rd;
            MEM_WB_result <= EX_MEM_alu_out;

            // WRITEBACK
            if (MEM_WB_instr[15:12] != 4'b0100) // Not STORE
                registers[MEM_WB_rd] <= MEM_WB_result;
        end
    end
endmodule

pipeline_tb.v
`timescale 1ns/1ps

module pipeline_tb;
    reg clk = 0;
    reg reset = 1;

    pipeline_processor uut (.clk(clk), .reset(reset));

    always #5 clk = ~clk;

    initial begin
        $dumpfile("wave.vcd");
        $dumpvars(0, pipeline_tb);

        // Wait a bit and release reset
        #10 reset = 0;

        // Initialize register file
        uut.registers[1] = 8'd10;
        uut.registers[2] = 8'd5;
        uut.data_memory[20] = 8'd100;

        // Load Instructions:
        // ADD R1 + R2 -> R3
        uut.instruction_memory[0] = 16'b0001_0001_0010_0011;

        // SUB R1 - R2 -> R4
        uut.instruction_memory[1] = 16'b0010_0001_0010_0100;

        // LOAD [R1] -> R5
        uut.instruction_memory[2] = 16'b0011_0001_0000_0101;

        // STORE R1 -> [R2]
        uut.instruction_memory[3] = 16'b0100_0001_0010_0000;

        // NOP
        uut.instruction_memory[4] = 16'b0000_0000_0000_0000;

        #100;

        // Display Results
        $display("R3 (ADD)  = %d", uut.registers[3]);  // Expect 15
        $display("R4 (SUB)  = %d", uut.registers[4]);  // Expect 5
        $display("R5 (LOAD) = %d", uut.registers[5]);  // Expect 100
        $display("Mem[5]    = %d", uut.data_memory[5]); // Should be unchanged
        $display("Mem[5]    = %d", uut.data_memory[2]); // Should contain 10 (store)

        $finish;
    end
endmodule

wave.vcd
$date
	Thu Jul 17 12:47:21 2025
$end
$version
	Icarus Verilog
$end
$timescale
	1ps
$end
$scope module pipeline_tb $end
$var reg 1 ! clk $end
$var reg 1 " reset $end
$scope module uut $end
$var wire 1 # clk $end
$var wire 4 $ opcode [3:0] $end
$var wire 4 % rd [3:0] $end
$var wire 1 & reset $end
$var wire 4 ' rs [3:0] $end
$var wire 4 ( rt [3:0] $end
$var reg 8 ) EX_MEM_alu_out [7:0] $end
$var reg 16 * EX_MEM_instr [15:0] $end
$var reg 4 + EX_MEM_rd [3:0] $end
$var reg 8 , EX_MEM_rt_val [7:0] $end
$var reg 16 - ID_EX_instr [15:0] $end
$var reg 4 . ID_EX_rd [3:0] $end
$var reg 8 / ID_EX_rs_val [7:0] $end
$var reg 8 0 ID_EX_rt_val [7:0] $end
$var reg 16 1 IF_ID_instr [15:0] $end
$var reg 16 2 MEM_WB_instr [15:0] $end
$var reg 4 3 MEM_WB_rd [3:0] $end
$var reg 8 4 MEM_WB_result [7:0] $end
$var reg 8 5 pc [7:0] $end
$upscope $end
$upscope $end
$enddefinitions $end
#0
$dumpvars
b0 5
bx 4
bx 3
b0 2
b0 1
bx 0
bx /
bx .
b0 -
bx ,
bx +
b0 *
bx )
b0 (
b0 '
1&
b0 %
b0 $
0#
1"
0!
$end
#5000
1!
1#
#10000
0!
0#
0"
0&
#15000
b1 $
b1 '
b10 (
b11 %
b0 )
b0 .
b1 5
b1000100100011 1
1!
1#
#20000
0!
0#
#25000
b10 $
b100 %
b0 4
b0 +
b11 .
b101 0
b1010 /
b1000100100011 -
b10 5
b10000100100100 1
1!
1#
#30000
0!
0#
#35000
b11 $
b0 (
b101 %
b0 3
b1111 )
b11 +
b101 ,
b1000100100011 *
b100 .
b10000100100100 -
b11 5
b11000100000101 1
1!
1#
#40000
0!
0#
#45000
b100 $
b10 (
b0 %
b1111 4
b11 3
b1000100100011 2
b101 )
b100 +
b10000100100100 *
b101 .
bx 0
b11000100000101 -
b100 5
b100000100100000 1
1!
1#
#50000
0!
0#
#55000
b0 $
b0 '
b0 (
b101 4
b100 3
b10000100100100 2
bx )
b101 +
bx ,
b11000100000101 *
b0 .
b101 0
b100000100100000 -
b101 5
b0 1
1!
1#
#60000
0!
0#
#65000
bx $
bx '
bx (
bx %
bx 4
b101 3
b11000100000101 2
b0 )
b0 +
b101 ,
b100000100100000 *
b0 0
b0 /
b0 -
b110 5
bx 1
1!
1#
#70000
0!
0#
#75000
b0 4
b0 3
b100000100100000 2
b0 ,
b0 *
bx .
bx 0
bx /
bx -
b111 5
1!
1#
#80000
0!
0#
#85000
b0 2
bx +
bx ,
bx *
b1000 5
1!
1#
#90000
0!
0#
#95000
bx 3
bx 2
b1001 5
1!
1#
#100000
0!
0#
#105000
b1010 5
1!
1#
